setup.py
tfdataset/__init__.py
tfdataset/action_recogntion_data.py
tfdataset/autoinjector.json
tfdataset/client.py
tfdataset/csv_to_tfrecords.py
tfdataset/cutter.py
tfdataset/dataset_utils.py
tfdataset/eye_drop.json
tfdataset/glucometer.json
tfdataset/key.pem
tfdataset/object_detection_data.py
tfdataset/pascal_voc_pb2.py
tfdataset/pascal_voc_pb2_grpc.py
tfdataset/star_inhandplus_com.crt
tfdataset/xml_to_csv.py
tfdataset.egg-info/PKG-INFO
tfdataset.egg-info/SOURCES.txt
tfdataset.egg-info/dependency_links.txt
tfdataset.egg-info/entry_points.txt
tfdataset.egg-info/not-zip-safe
tfdataset.egg-info/requires.txt
tfdataset.egg-info/top_level.txt